commitizen_wheel_provider.py
commitizen_wheel_provider-0.1.0.dist-info/METADATA
commitizen_wheel_provider-0.1.0.dist-info/WHEEL
commitizen_wheel_provider-0.1.0.dist-info/entry_points.txt
commitizen_wheel_provider-0.1.0.dist-info/licenses/LICENSE
commitizen_wheel_provider-0.1.0.dist-info/RECORD
