Metadata-Version: 2.4
Name: commitizen-wheel-provider
Version: 0.1.0
Summary: A commitizen provider based on wheel metadata.
Project-URL: Repository, https://github.com/hmiladhia/commitizen-wheel-provider
Project-URL: Issues, https://github.com/hmiladhia/commitizen-wheel-provider/issues
Author: Dhia Hmila
License: MIT License
License-File: LICENSE
Classifier: Intended Audience :: Developers
Classifier: License :: OSI Approved :: MIT License
Classifier: Programming Language :: Python :: 3
Classifier: Programming Language :: Python :: 3.9
Classifier: Programming Language :: Python :: 3.10
Classifier: Programming Language :: Python :: 3.11
Classifier: Programming Language :: Python :: 3.12
Classifier: Programming Language :: Python :: 3.13
Requires-Python: >=3.9
Requires-Dist: build-wheel-metadata>=0.0.1
Requires-Dist: commitizen>=4.0.0
